evekeys/__init__.py
evekeys/evekeys.py
evekeys-0.0.2.dist-info/LICENSE
evekeys-0.0.2.dist-info/METADATA
evekeys-0.0.2.dist-info/WHEEL
evekeys-0.0.2.dist-info/top_level.txt
evekeys-0.0.2.dist-info/RECORD
