Metadata-Version: 2.1
Name: evekeys
Version: 0.0.2
Summary: A set of functions that uses sklearn to conduct a TF-IDF analysis to generate keywords from event-based / grouped textual corpus.
Home-page: https://github.com/lingeringcode/evekeys/
Author: Chris A. Lindgren
Author-email: chris.a.lindgren@gmail.com
License: UNKNOWN
Download-URL: https://github.com/lingeringcode/evekeys/
Keywords: tf-idf,keyword extraction,event-based corpus
Platform: UNKNOWN
Requires-Dist: pandas
Requires-Dist: sklearn
Requires-Dist: tqdm
